zoy/__init__.py
zoy/__main__.py
zoy/zoy.py
zoy-0.2.0.dist-info/entry_points.txt
zoy-0.2.0.dist-info/METADATA
zoy-0.2.0.dist-info/WHEEL
zoy-0.2.0.dist-info/RECORD
